{"progress":{"state":"COMPLETED","status":"","start":{"seconds":"1542812152","nanos":497611000},"end":{"seconds":"1542812155","nanos":783611000}},"steps":[],"exposed_outputs":{"steps.0.produce":{"value":"csv_uri","error":null,"raw":null,"dataset_uri":"","csv_uri":"file:///output/predictions/fde0e76b-7210-4ab5-a895-32dda338f29c/fde0e76b-7210-4ab5-a895-32dda338f29c.steps.0.produce.csv","pickle_uri":"","pickle_blob":{"type":"Buffer","data":[]},"plasma_id":{"type":"Buffer","data":[]}}},"fitted_solution_id":"fde0e76b-7210-4ab5-a895-32dda338f29c"}