{"progress":{"state":"COMPLETED","status":"","start":{"seconds":"1542808834","nanos":663385000},"end":{"seconds":"1542808836","nanos":687478000}},"steps":[],"exposed_outputs":{"steps.0.produce":{"value":"csv_uri","error":null,"raw":null,"dataset_uri":"","csv_uri":"file:///output/predictions/26a84a84-cb8a-4417-8b41-52719eef5e8e/26a84a84-cb8a-4417-8b41-52719eef5e8e.steps.0.produce.csv","pickle_uri":"","pickle_blob":{"type":"Buffer","data":[]},"plasma_id":{"type":"Buffer","data":[]}}},"fitted_solution_id":"26a84a84-cb8a-4417-8b41-52719eef5e8e"}